setup.py
src/serf/__init__.py
src/serf/_exceptions.py
src/serf/client.py
src/serf/command_handler.py
src/serf/connection.py
src/serf/constant.py
src/serf/request.py
src/serf/response.py
src/serf_python.egg-info/PKG-INFO
src/serf_python.egg-info/SOURCES.txt
src/serf_python.egg-info/dependency_links.txt
src/serf_python.egg-info/requires.txt
src/serf_python.egg-info/top_level.txt
test/test_base.py
test/test_command_auth.py
test/test_command_event.py
test/test_command_force_leave.py
test/test_command_handshake.py
test/test_command_join.py
test/test_command_leave.py
test/test_command_members.py
test/test_command_monitor.py
test/test_command_query.py
test/test_command_respond.py
test/test_command_stop.py
test/test_command_stream.py
test/test_common.py
test/test_context_manager.py
test/test_request.py
test/test_stop_receive_data.py