Metadata-Version: 1.0
Name: serf-python
Version: 0.2.2
Summary: serf client for python
Home-page: https://github.com/spikeekips/serf-python
Author: Spike^ekipS
Author-email: spikeekips@gmail.com
License: License :: OSI Approved :: Mozilla Public License 2.0 (MPL 2.0)
Platform: UNKNOWN
